smart_building_rating_calculator/__init__.py
smart_building_rating_calculator/calculate_sbr_score.py
smart_building_rating_calculator/flex_archetype.py
smart_building_rating_calculator/flexer_enums.py
smart_building_rating_calculator/initiate_user_inputs.py
smart_building_rating_calculator/inputs.py
smart_building_rating_calculator/intermediate_scoring.py
smart_building_rating_calculator-0.0.0.dist-info/LICENSE
smart_building_rating_calculator-0.0.0.dist-info/METADATA
smart_building_rating_calculator-0.0.0.dist-info/WHEEL
smart_building_rating_calculator-0.0.0.dist-info/top_level.txt
smart_building_rating_calculator-0.0.0.dist-info/RECORD
