Metadata-Version: 2.1
Name: smart-building-rating-calculator
Version: 0.0.0
Summary: The calculation to generate a smart building rating
Home-page: https://github.com/centrefornetzero/smart-building-rating-calculator
Author: Centre for Net Zero
Author-email: data@centrefornetzero.org
Classifier: Programming Language :: Python :: 3
Classifier: License :: OSI Approved :: MIT License
Classifier: Operating System :: OS Independent
Requires-Python: >=3.11
License-File: LICENSE
Requires-Dist: pandas >=2.2
